Workbook

Sheet PERFILES
A1: IDENTIFICACION | G1: GRUPOS A GENERAR (SI / NO) | P1: DATOS TECNICOS | U1: PLANOS | W1: COMPONENTES ESTRUCTURA | AF1: COMERCIAL | AK1: MINIMOS ALMACEN | AN1: ANEXOS | AP1: DIVISORES PVP (manuales por perfil) | AY1: COSTE (euros/m) — automatico | BH1: PVP TARIFA (euros/m) — automatico | BQ1: CONTROL GENERACION
A2: REF | B2: FAMILIA | C2: DENOMINACION | D2: CLASE/SERIE | E2: NORMA | F2: ESTADO GEINFOR | G2: G0 BT | H2: G1 PL | I2: G2 BR | J2: G3 BL | K2: G4 ASP | L2: G6 STD | M2: G7 ESP | N2: G8 BI | O2: G9 MAD | P2: PESO kg/m | Q2: LONGITUD m/barra | R2: PERIM. TOTAL m | S2: PERIM. EXT. m | T2: N CARAS | U2: PLANO | V2: PLANO ORIGINAL | W2: POLI 1 | X2: CANT POLI 1 | Y2: POLI 2 | Z2: CANT POLI 2 | AA2: COMP 1 | AB2: CANT COMP 1 | AC2: COMP 2 | AD2: CANT COMP 2 | AE2: MECANIZADO | AF2: PROVEEDOR | AG2: REF. PROV. | AH2: LOTE HABITUAL | AI2: PLAZO DIAS | AJ2: PARTIDA ARANC. | AK2: MIN BRUTO | AL2: MIN BLANCO | AM2: MIN PLATA | AN2: ANEXO | AO2: VALOR ANEXO | AP2: DIV BT | AQ2: DIV PL | AR2: DIV BR | AS2: DIV BL | AT2: DIV ASP | AU2: DIV STD | AV2: DIV ESP | AW2: DIV BI | AX2: DIV MAD | AY2: BT | AZ2: PL | BA2: BR | BB2: BL | BC2: ASP | BD2: STD | BE2: ESP | BF2: BI | BG2: MAD | BH2: BT | BI2: PL | BJ2: BR | BK2: BL | BL2: ASP | BM2: STD | BN2: ESP | BO2: BI | BP2: MAD | BQ2: ESTADO | BR2: FECHA GENER. | BS2: NOTAS
A3: A0004750 | B3: 1 | C3: SOLAPE FICTIO | D3: 51 | E3: EU | F3: 70 | G3: SI | H3: SI | I3: SI | J3: SI | K3: SI | L3: SI | M3: SI | N3: NO | O3: SI | P3: 0.35 | Q3: 6.3 | R3: 0.2 | S3: 0.2 | T3: 2 | U3: =IF($A3="","","X:\IMAGENES GEINPROD\"&$A3&".JPG") -> X:\IMAGENES GEINPROD\A0004750.JPG | V3: =IF($A3="","","X:\IMAGENES GEINPROD\PLANO ORIGINAL THERMIA\"&$A3&".pdf") -> X:\IMAGENES GEINPROD\PLANO ORIGINAL THERMIA\A0004750.pdf | AF3: TOLEDO | AG3: PROVISIONAL | AH3: 500 | AI3: 25 | AJ3: 1 | AK3: 300 | AL3: 50 | AM3: 20 | AN3: 100 | AO3: TH | AP3: 0.42 | AQ3: 0.42 | AR3: 0.44 | AS3: 0.43 | AT3: 0.44 | AU3: 0.43 | AV3: 0.44 | AX3: 0.42 | AY3: =IF($A3="","",ROUND(P3*CONFIGURACION!$B$2+IF(W3<>"",X3*IFERROR(VLOOKUP(W3,'DATOS COSTES POLIAMIDAS'!$A:$G,7,0),0),0)+IF(Y3<>"",Z3*IFERROR(VLOOKUP(Y3,'DATOS COSTES POLIAMIDAS'!$A:$G,7,0),0),0)+IF(AA3<>"",AB3*IFERROR(VLOOKUP(AA3,'DATOS COSTES POLIAMIDAS'!$A:$G,7,0),0),0)+IF(AC3<>"",AD3*IFERROR(VLOOKUP(AC3,'DATOS COSTES POLIAMIDAS'!$A:$G,7,0),0),0)+IF(AE3<>"",IFERROR(VLOOKUP(AE3,'DATOS COSTES MECANIZADOS'!$A:$F,6,0),0),0),4)) -> 1.799 | AZ3: =IF($A3="","",ROUND(AY3+R3*CONFIGURACION!$B$6,4)) -> 2.497 | BA3: =IF($A3="","",ROUND(AY3+R3*CONFIGURACION!$B$7,4)) -> 2.931 | BB3: =IF($A3="","",ROUND(AY3+R3*CONFIGURACION!$B$5,4)) -> 2.1282 | BC3: =IF($A3="","",ROUND(AY3+R3*CONFIGURACION!$B$10+R3*T3*CONFIGURACION!$B$11,4)) -> 3.135 | BD3: =IF($A3="","",ROUND(AY3+R3*CONFIGURACION!$B$8,4)) -> 2.3404 | BE3: =IF($A3="","",ROUND(AY3+R3*CONFIGURACION!$B$9,4)) -> 2.681 | BF3: =IF($A3="","",ROUND(AY3+R3*CONFIGURACION!$B$13,4)) -> 1.799 | BG3: =IF($A3="","",ROUND(AY3+R3*CONFIGURACION!$B$12,4)) -> 2.999 | BH3: =IF($A3="","",IF(AP3="","",ROUND(AY3/AP3,4))) -> 4.2833 | BI3: =IF($A3="","",IF(AQ3="","",ROUND(AZ3/AQ3,4))) -> 5.9452 | BJ3: =IF($A3="","",IF(AR3="","",ROUND(BA3/AR3,4))) -> 6.6614 | BK3: =IF($A3="","",IF(AS3="","",ROUND(BB3/AS3,4))) -> 4.9493 | BL3: =IF($A3="","",IF(AT3="","",ROUND(BC3/AT3,4))) -> 7.125 | BM3: =IF($A3="","",IF(AU3="","",ROUND(BD3/AU3,4))) -> 5.4428 | BN3: =IF($A3="","",IF(AV3="","",ROUND(BE3/AV3,4))) -> 6.0932 | BO3: =IF($A3="","",IF(AW3="","",ROUND(BF3/AW3,4))) | BP3: =IF($A3="","",IF(AX3="","",ROUND(BG3/AX3,4))) -> 7.1405 | BQ3: LISTO | BR3: 46218 | BS3: PRUEBA
U4: =IF($A4="","","X:\IMAGENES GEINPROD\"&$A4&".JPG") | V4: =IF($A4="","","X:\IMAGENES GEINPROD\PLANO ORIGINAL THERMIA\"&$A4&".pdf") | AY4: =IF($A4="","",ROUND(P4*CONFIGURACION!$B$2+IF(W4<>"",X4*IFERROR(VLOOKUP(W4,'DATOS COSTES POLIAMIDAS'!$A:$G,7,0),0),0)+IF(Y4<>"",Z4*IFERROR(VLOOKUP(Y4,'DATOS COSTES POLIAMIDAS'!$A:$G,7,0),0),0)+IF(AA4<>"",AB4*IFERROR(VLOOKUP(AA4,'DATOS COSTES POLIAMIDAS'!$A:$G,7,0),0),0)+IF(AC4<>"",AD4*IFERROR(VLOOKUP(AC4,'DATOS COSTES POLIAMIDAS'!$A:$G,7,0),0),0)+IF(AE4<>"",IFERROR(VLOOKUP(AE4,'DATOS COSTES MECANIZADOS'!$A:$F,6,0),0),0),4)) | AZ4: =IF($A4="","",ROUND(AY4+R4*CONFIGURACION!$B$6,4)) | BA4: =IF($A4="","",ROUND(AY4+R4*CONFIGURACION!$B$7,4)) | BB4: =IF($A4="","",ROUND(AY4+R4*CONFIGURACION!$B$5,4)) | BC4: =IF($A4="","",ROUND(AY4+R4*CONFIGURACION!$B$10+R4*T4*CONFIGURACION!$B$11,4)) | BD4: =IF($A4="","",ROUND(AY4+R4*CONFIGURACION!$B$8,4)) | BE4: =IF($A4="","",ROUND(AY4+R4*CONFIGURACION!$B$9,4)) | BF4: =IF($A4="","",ROUND(AY4+R4*CONFIGURACION!$B$13,4)) | BG4: =IF($A4="","",ROUND(AY4+R4*CONFIGURACION!$B$12,4)) | BH4: =IF($A4="","",IF(AP4="","",ROUND(AY4/AP4,4))) | BI4: =IF($A4="","",IF(AQ4="","",ROUND(AZ4/AQ4,4))) | BJ4: =IF($A4="","",IF(AR4="","",ROUND(BA4/AR4,4))) | BK4: =IF($A4="","",IF(AS4="","",ROUND(BB4/AS4,4))) | BL4: =IF($A4="","",IF(AT4="","",ROUND(BC4/AT4,4))) | BM4: =IF($A4="","",IF(AU4="","",ROUND(BD4/AU4,4))) | BN4: =IF($A4="","",IF(AV4="","",ROUND(BE4/AV4,4))) | BO4: =IF($A4="","",IF(AW4="","",ROUND(BF4/AW4,4))) | BP4: =IF($A4="","",IF(AX4="","",ROUND(BG4/AX4,4)))
U5: =IF($A5="","","X:\IMAGENES GEINPROD\"&$A5&".JPG") | V5: =IF($A5="","","X:\IMAGENES GEINPROD\PLANO ORIGINAL THERMIA\"&$A5&".pdf") | AY5: =IF($A5="","",ROUND(P5*CONFIGURACION!$B$2+IF(W5<>"",X5*IFERROR(VLOOKUP(W5,'DATOS COSTES POLIAMIDAS'!$A:$G,7,0),0),0)+IF(Y5<>"",Z5*IFERROR(VLOOKUP(Y5,'DATOS COSTES POLIAMIDAS'!$A:$G,7,0),0),0)+IF(AA5<>"",AB5*IFERROR(VLOOKUP(AA5,'DATOS COSTES POLIAMIDAS'!$A:$G,7,0),0),0)+IF(AC5<>"",AD5*IFERROR(VLOOKUP(AC5,'DATOS COSTES POLIAMIDAS'!$A:$G,7,0),0),0)+IF(AE5<>"",IFERROR(VLOOKUP(AE5,'DATOS COSTES MECANIZADOS'!$A:$F,6,0),0),0),4)) | AZ5: =IF($A5="","",ROUND(AY5+R5*CONFIGURACION!$B$6,4)) | BA5: =IF($A5="","",ROUND(AY5+R5*CONFIGURACION!$B$7,4)) | BB5: =IF($A5="","",ROUND(AY5+R5*CONFIGURACION!$B$5,4)) | BC5: =IF($A5="","",ROUND(AY5+R5*CONFIGURACION!$B$10+R5*T5*CONFIGURACION!$B$11,4)) | BD5: =IF($A5="","",ROUND(AY5+R5*CONFIGURACION!$B$8,4)) | BE5: =IF($A5="","",ROUND(AY5+R5*CONFIGURACION!$B$9,4)) | BF5: =IF($A5="","",ROUND(AY5+R5*CONFIGURACION!$B$13,4)) | BG5: =IF($A5="","",ROUND(AY5+R5*CONFIGURACION!$B$12,4)) | BH5: =IF($A5="","",IF(AP5="","",ROUND(AY5/AP5,4))) | BI5: =IF($A5="","",IF(AQ5="","",ROUND(AZ5/AQ5,4))) | BJ5: =IF($A5="","",IF(AR5="","",ROUND(BA5/AR5,4))) | BK5: =IF($A5="","",IF(AS5="","",ROUND(BB5/AS5,4))) | BL5: =IF($A5="","",IF(AT5="","",ROUND(BC5/AT5,4))) | BM5: =IF($A5="","",IF(AU5="","",ROUND(BD5/AU5,4))) | BN5: =IF($A5="","",IF(AV5="","",ROUND(BE5/AV5,4))) | BO5: =IF($A5="","",IF(AW5="","",ROUND(BF5/AW5,4))) | BP5: =IF($A5="","",IF(AX5="","",ROUND(BG5/AX5,4)))
U6: =IF($A6="","","X:\IMAGENES GEINPROD\"&$A6&".JPG") | V6: =IF($A6="","","X:\IMAGENES GEINPROD\PLANO ORIGINAL THERMIA\"&$A6&".pdf") | AY6: =IF($A6="","",ROUND(P6*CONFIGURACION!$B$2+IF(W6<>"",X6*IFERROR(VLOOKUP(W6,'DATOS COSTES POLIAMIDAS'!$A:$G,7,0),0),0)+IF(Y6<>"",Z6*IFERROR(VLOOKUP(Y6,'DATOS COSTES POLIAMIDAS'!$A:$G,7,0),0),0)+IF(AA6<>"",AB6*IFERROR(VLOOKUP(AA6,'DATOS COSTES POLIAMIDAS'!$A:$G,7,0),0),0)+IF(AC6<>"",AD6*IFERROR(VLOOKUP(AC6,'DATOS COSTES POLIAMIDAS'!$A:$G,7,0),0),0)+IF(AE6<>"",IFERROR(VLOOKUP(AE6,'DATOS COSTES MECANIZADOS'!$A:$F,6,0),0),0),4)) | AZ6: =IF($A6="","",ROUND(AY6+R6*CONFIGURACION!$B$6,4)) | BA6: =IF($A6="","",ROUND(AY6+R6*CONFIGURACION!$B$7,4)) | BB6: =IF($A6="","",ROUND(AY6+R6*CONFIGURACION!$B$5,4)) | BC6: =IF($A6="","",ROUND(AY6+R6*CONFIGURACION!$B$10+R6*T6*CONFIGURACION!$B$11,4)) | BD6: =IF($A6="","",ROUND(AY6+R6*CONFIGURACION!$B$8,4)) | BE6: =IF($A6="","",ROUND(AY6+R6*CONFIGURACION!$B$9,4)) | BF6: =IF($A6="","",ROUND(AY6+R6*CONFIGURACION!$B$13,4)) | BG6: =IF($A6="","",ROUND(AY6+R6*CONFIGURACION!$B$12,4)) | BH6: =IF($A6="","",IF(AP6="","",ROUND(AY6/AP6,4))) | BI6: =IF($A6="","",IF(AQ6="","",ROUND(AZ6/AQ6,4))) | BJ6: =IF($A6="","",IF(AR6="","",ROUND(BA6/AR6,4))) | BK6: =IF($A6="","",IF(AS6="","",ROUND(BB6/AS6,4))) | BL6: =IF($A6="","",IF(AT6="","",ROUND(BC6/AT6,4))) | BM6: =IF($A6="","",IF(AU6="","",ROUND(BD6/AU6,4))) | BN6: =IF($A6="","",IF(AV6="","",ROUND(BE6/AV6,4))) | BO6: =IF($A6="","",IF(AW6="","",ROUND(BF6/AW6,4))) | BP6: =IF($A6="","",IF(AX6="","",ROUND(BG6/AX6,4)))
U7: =IF($A7="","","X:\IMAGENES GEINPROD\"&$A7&".JPG") | V7: =IF($A7="","","X:\IMAGENES GEINPROD\PLANO ORIGINAL THERMIA\"&$A7&".pdf") | AY7: =IF($A7="","",ROUND(P7*CONFIGURACION!$B$2+IF(W7<>"",X7*IFERROR(VLOOKUP(W7,'DATOS COSTES POLIAMIDAS'!$A:$G,7,0),0),0)+IF(Y7<>"",Z7*IFERROR(VLOOKUP(Y7,'DATOS COSTES POLIAMIDAS'!$A:$G,7,0),0),0)+IF(AA7<>"",AB7*IFERROR(VLOOKUP(AA7,'DATOS COSTES POLIAMIDAS'!$A:$G,7,0),0),0)+IF(AC7<>"",AD7*IFERROR(VLOOKUP(AC7,'DATOS COSTES POLIAMIDAS'!$A:$G,7,0),0),0)+IF(AE7<>"",IFERROR(VLOOKUP(AE7,'DATOS COSTES MECANIZADOS'!$A:$F,6,0),0),0),4)) | AZ7: =IF($A7="","",ROUND(AY7+R7*CONFIGURACION!$B$6,4)) | BA7: =IF($A7="","",ROUND(AY7+R7*CONFIGURACION!$B$7,4)) | BB7: =IF($A7="","",ROUND(AY7+R7*CONFIGURACION!$B$5,4)) | BC7: =IF($A7="","",ROUND(AY7+R7*CONFIGURACION!$B$10+R7*T7*CONFIGURACION!$B$11,4)) | BD7: =IF($A7="","",ROUND(AY7+R7*CONFIGURACION!$B$8,4)) | BE7: =IF($A7="","",ROUND(AY7+R7*CONFIGURACION!$B$9,4)) | BF7: =IF($A7="","",ROUND(AY7+R7*CONFIGURACION!$B$13,4)) | BG7: =IF($A7="","",ROUND(AY7+R7*CONFIGURACION!$B$12,4)) | BH7: =IF($A7="","",IF(AP7="","",ROUND(AY7/AP7,4))) | BI7: =IF($A7="","",IF(AQ7="","",ROUND(AZ7/AQ7,4))) | BJ7: =IF($A7="","",IF(AR7="","",ROUND(BA7/AR7,4))) | BK7: =IF($A7="","",IF(AS7="","",ROUND(BB7/AS7,4))) | BL7: =IF($A7="","",IF(AT7="","",ROUND(BC7/AT7,4))) | BM7: =IF($A7="","",IF(AU7="","",ROUND(BD7/AU7,4))) | BN7: =IF($A7="","",IF(AV7="","",ROUND(BE7/AV7,4))) | BO7: =IF($A7="","",IF(AW7="","",ROUND(BF7/AW7,4))) | BP7: =IF($A7="","",IF(AX7="","",ROUND(BG7/AX7,4)))
U8: =IF($A8="","","X:\IMAGENES GEINPROD\"&$A8&".JPG") | V8: =IF($A8="","","X:\IMAGENES GEINPROD\PLANO ORIGINAL THERMIA\"&$A8&".pdf") | AY8: =IF($A8="","",ROUND(P8*CONFIGURACION!$B$2+IF(W8<>"",X8*IFERROR(VLOOKUP(W8,'DATOS COSTES POLIAMIDAS'!$A:$G,7,0),0),0)+IF(Y8<>"",Z8*IFERROR(VLOOKUP(Y8,'DATOS COSTES POLIAMIDAS'!$A:$G,7,0),0),0)+IF(AA8<>"",AB8*IFERROR(VLOOKUP(AA8,'DATOS COSTES POLIAMIDAS'!$A:$G,7,0),0),0)+IF(AC8<>"",AD8*IFERROR(VLOOKUP(AC8,'DATOS COSTES POLIAMIDAS'!$A:$G,7,0),0),0)+IF(AE8<>"",IFERROR(VLOOKUP(AE8,'DATOS COSTES MECANIZADOS'!$A:$F,6,0),0),0),4)) | AZ8: =IF($A8="","",ROUND(AY8+R8*CONFIGURACION!$B$6,4)) | BA8: =IF($A8="","",ROUND(AY8+R8*CONFIGURACION!$B$7,4)) | BB8: =IF($A8="","",ROUND(AY8+R8*CONFIGURACION!$B$5,4)) | BC8: =IF($A8="","",ROUND(AY8+R8*CONFIGURACION!$B$10+R8*T8*CONFIGURACION!$B$11,4)) | BD8: =IF($A8="","",ROUND(AY8+R8*CONFIGURACION!$B$8,4)) | BE8: =IF($A8="","",ROUND(AY8+R8*CONFIGURACION!$B$9,4)) | BF8: =IF($A8="","",ROUND(AY8+R8*CONFIGURACION!$B$13,4)) | BG8: =IF($A8="","",ROUND(AY8+R8*CONFIGURACION!$B$12,4)) | BH8: =IF($A8="","",IF(AP8="","",ROUND(AY8/AP8,4))) | BI8: =IF($A8="","",IF(AQ8="","",ROUND(AZ8/AQ8,4))) | BJ8: =IF($A8="","",IF(AR8="","",ROUND(BA8/AR8,4))) | BK8: =IF($A8="","",IF(AS8="","",ROUND(BB8/AS8,4))) | BL8: =IF($A8="","",IF(AT8="","",ROUND(BC8/AT8,4))) | BM8: =IF($A8="","",IF(AU8="","",ROUND(BD8/AU8,4))) | BN8: =IF($A8="","",IF(AV8="","",ROUND(BE8/AV8,4))) | BO8: =IF($A8="","",IF(AW8="","",ROUND(BF8/AW8,4))) | BP8: =IF($A8="","",IF(AX8="","",ROUND(BG8/AX8,4)))
U9: =IF($A9="","","X:\IMAGENES GEINPROD\"&$A9&".JPG") | V9: =IF($A9="","","X:\IMAGENES GEINPROD\PLANO ORIGINAL THERMIA\"&$A9&".pdf") | AY9: =IF($A9="","",ROUND(P9*CONFIGURACION!$B$2+IF(W9<>"",X9*IFERROR(VLOOKUP(W9,'DATOS COSTES POLIAMIDAS'!$A:$G,7,0),0),0)+IF(Y9<>"",Z9*IFERROR(VLOOKUP(Y9,'DATOS COSTES POLIAMIDAS'!$A:$G,7,0),0),0)+IF(AA9<>"",AB9*IFERROR(VLOOKUP(AA9,'DATOS COSTES POLIAMIDAS'!$A:$G,7,0),0),0)+IF(AC9<>"",AD9*IFERROR(VLOOKUP(AC9,'DATOS COSTES POLIAMIDAS'!$A:$G,7,0),0),0)+IF(AE9<>"",IFERROR(VLOOKUP(AE9,'DATOS COSTES MECANIZADOS'!$A:$F,6,0),0),0),4)) | AZ9: =IF($A9="","",ROUND(AY9+R9*CONFIGURACION!$B$6,4)) | BA9: =IF($A9="","",ROUND(AY9+R9*CONFIGURACION!$B$7,4)) | BB9: =IF($A9="","",ROUND(AY9+R9*CONFIGURACION!$B$5,4)) | BC9: =IF($A9="","",ROUND(AY9+R9*CONFIGURACION!$B$10+R9*T9*CONFIGURACION!$B$11,4)) | BD9: =IF($A9="","",ROUND(AY9+R9*CONFIGURACION!$B$8,4)) | BE9: =IF($A9="","",ROUND(AY9+R9*CONFIGURACION!$B$9,4)) | BF9: =IF($A9="","",ROUND(AY9+R9*CONFIGURACION!$B$13,4)) | BG9: =IF($A9="","",ROUND(AY9+R9*CONFIGURACION!$B$12,4)) | BH9: =IF($A9="","",IF(AP9="","",ROUND(AY9/AP9,4))) | BI9: =IF($A9="","",IF(AQ9="","",ROUND(AZ9/AQ9,4))) | BJ9: =IF($A9="","",IF(AR9="","",ROUND(BA9/AR9,4))) | BK9: =IF($A9="","",IF(AS9="","",ROUND(BB9/AS9,4))) | BL9: =IF($A9="","",IF(AT9="","",ROUND(BC9/AT9,4))) | BM9: =IF($A9="","",IF(AU9="","",ROUND(BD9/AU9,4))) | BN9: =IF($A9="","",IF(AV9="","",ROUND(BE9/AV9,4))) | BO9: =IF($A9="","",IF(AW9="","",ROUND(BF9/AW9,4))) | BP9: =IF($A9="","",IF(AX9="","",ROUND(BG9/AX9,4)))
U10: =IF($A10="","","X:\IMAGENES GEINPROD\"&$A10&".JPG") | V10: =IF($A10="","","X:\IMAGENES GEINPROD\PLANO ORIGINAL THERMIA\"&$A10&".pdf") | AY10: =IF($A10="","",ROUND(P10*CONFIGURACION!$B$2+IF(W10<>"",X10*IFERROR(VLOOKUP(W10,'DATOS COSTES POLIAMIDAS'!$A:$G,7,0),0),0)+IF(Y10<>"",Z10*IFERROR(VLOOKUP(Y10,'DATOS COSTES POLIAMIDAS'!$A:$G,7,0),0),0)+IF(AA10<>"",AB10*IFERROR(VLOOKUP(AA10,'DATOS COSTES POLIAMIDAS'!$A:$G,7,0),0),0)+IF(AC10<>"",AD10*IFERROR(VLOOKUP(AC10,'DATOS COSTES POLIAMIDAS'!$A:$G,7,0),0),0)+IF(AE10<>"",IFERROR(VLOOKUP(AE10,'DATOS COSTES MECANIZADOS'!$A:$F,6,0),0),0),4)) | AZ10: =IF($A10="","",ROUND(AY10+R10*CONFIGURACION!$B$6,4)) | BA10: =IF($A10="","",ROUND(AY10+R10*CONFIGURACION!$B$7,4)) | BB10: =IF($A10="","",ROUND(AY10+R10*CONFIGURACION!$B$5,4)) | BC10: =IF($A10="","",ROUND(AY10+R10*CONFIGURACION!$B$10+R10*T10*CONFIGURACION!$B$11,4)) | BD10: =IF($A10="","",ROUND(AY10+R10*CONFIGURACION!$B$8,4)) | BE10: =IF($A10="","",ROUND(AY10+R10*CONFIGURACION!$B$9,4)) | BF10: =IF($A10="","",ROUND(AY10+R10*CONFIGURACION!$B$13,4)) | BG10: =IF($A10="","",ROUND(AY10+R10*CONFIGURACION!$B$12,4)) | BH10: =IF($A10="","",IF(AP10="","",ROUND(AY10/AP10,4))) | BI10: =IF($A10="","",IF(AQ10="","",ROUND(AZ10/AQ10,4))) | BJ10: =IF($A10="","",IF(AR10="","",ROUND(BA10/AR10,4))) | BK10: =IF($A10="","",IF(AS10="","",ROUND(BB10/AS10,4))) | BL10: =IF($A10="","",IF(AT10="","",ROUND(BC10/AT10,4))) | BM10: =IF($A10="","",IF(AU10="","",ROUND(BD10/AU10,4))) | BN10: =IF($A10="","",IF(AV10="","",ROUND(BE10/AV10,4))) | BO10: =IF($A10="","",IF(AW10="","",ROUND(BF10/AW10,4))) | BP10: =IF($A10="","",IF(AX10="","",ROUND(BG10/AX10,4)))
U11: =IF($A11="","","X:\IMAGENES GEINPROD\"&$A11&".JPG") | V11: =IF($A11="","","X:\IMAGENES GEINPROD\PLANO ORIGINAL THERMIA\"&$A11&".pdf") | AY11: =IF($A11="","",ROUND(P11*CONFIGURACION!$B$2+IF(W11<>"",X11*IFERROR(VLOOKUP(W11,'DATOS COSTES POLIAMIDAS'!$A:$G,7,0),0),0)+IF(Y11<>"",Z11*IFERROR(VLOOKUP(Y11,'DATOS COSTES POLIAMIDAS'!$A:$G,7,0),0),0)+IF(AA11<>"",AB11*IFERROR(VLOOKUP(AA11,'DATOS COSTES POLIAMIDAS'!$A:$G,7,0),0),0)+IF(AC11<>"",AD11*IFERROR(VLOOKUP(AC11,'DATOS COSTES POLIAMIDAS'!$A:$G,7,0),0),0)+IF(AE11<>"",IFERROR(VLOOKUP(AE11,'DATOS COSTES MECANIZADOS'!$A:$F,6,0),0),0),4)) | AZ11: =IF($A11="","",ROUND(AY11+R11*CONFIGURACION!$B$6,4)) | BA11: =IF($A11="","",ROUND(AY11+R11*CONFIGURACION!$B$7,4)) | BB11: =IF($A11="","",ROUND(AY11+R11*CONFIGURACION!$B$5,4)) | BC11: =IF($A11="","",ROUND(AY11+R11*CONFIGURACION!$B$10+R11*T11*CONFIGURACION!$B$11,4)) | BD11: =IF($A11="","",ROUND(AY11+R11*CONFIGURACION!$B$8,4)) | BE11: =IF($A11="","",ROUND(AY11+R11*CONFIGURACION!$B$9,4)) | BF11: =IF($A11="","",ROUND(AY11+R11*CONFIGURACION!$B$13,4)) | BG11: =IF($A11="","",ROUND(AY11+R11*CONFIGURACION!$B$12,4)) | BH11: =IF($A11="","",IF(AP11="","",ROUND(AY11/AP11,4))) | BI11: =IF($A11="","",IF(AQ11="","",ROUND(AZ11/AQ11,4))) | BJ11: =IF($A11="","",IF(AR11="","",ROUND(BA11/AR11,4))) | BK11: =IF($A11="","",IF(AS11="","",ROUND(BB11/AS11,4))) | BL11: =IF($A11="","",IF(AT11="","",ROUND(BC11/AT11,4))) | BM11: =IF($A11="","",IF(AU11="","",ROUND(BD11/AU11,4))) | BN11: =IF($A11="","",IF(AV11="","",ROUND(BE11/AV11,4))) | BO11: =IF($A11="","",IF(AW11="","",ROUND(BF11/AW11,4))) | BP11: =IF($A11="","",IF(AX11="","",ROUND(BG11/AX11,4)))
U12: =IF($A12="","","X:\IMAGENES GEINPROD\"&$A12&".JPG") | V12: =IF($A12="","","X:\IMAGENES GEINPROD\PLANO ORIGINAL THERMIA\"&$A12&".pdf") | AY12: =IF($A12="","",ROUND(P12*CONFIGURACION!$B$2+IF(W12<>"",X12*IFERROR(VLOOKUP(W12,'DATOS COSTES POLIAMIDAS'!$A:$G,7,0),0),0)+IF(Y12<>"",Z12*IFERROR(VLOOKUP(Y12,'DATOS COSTES POLIAMIDAS'!$A:$G,7,0),0),0)+IF(AA12<>"",AB12*IFERROR(VLOOKUP(AA12,'DATOS COSTES POLIAMIDAS'!$A:$G,7,0),0),0)+IF(AC12<>"",AD12*IFERROR(VLOOKUP(AC12,'DATOS COSTES POLIAMIDAS'!$A:$G,7,0),0),0)+IF(AE12<>"",IFERROR(VLOOKUP(AE12,'DATOS COSTES MECANIZADOS'!$A:$F,6,0),0),0),4)) | AZ12: =IF($A12="","",ROUND(AY12+R12*CONFIGURACION!$B$6,4)) | BA12: =IF($A12="","",ROUND(AY12+R12*CONFIGURACION!$B$7,4)) | BB12: =IF($A12="","",ROUND(AY12+R12*CONFIGURACION!$B$5,4)) | BC12: =IF($A12="","",ROUND(AY12+R12*CONFIGURACION!$B$10+R12*T12*CONFIGURACION!$B$11,4)) | BD12: =IF($A12="","",ROUND(AY12+R12*CONFIGURACION!$B$8,4)) | BE12: =IF($A12="","",ROUND(AY12+R12*CONFIGURACION!$B$9,4)) | BF12: =IF($A12="","",ROUND(AY12+R12*CONFIGURACION!$B$13,4)) | BG12: =IF($A12="","",ROUND(AY12+R12*CONFIGURACION!$B$12,4)) | BH12: =IF($A12="","",IF(AP12="","",ROUND(AY12/AP12,4))) | BI12: =IF($A12="","",IF(AQ12="","",ROUND(AZ12/AQ12,4))) | BJ12: =IF($A12="","",IF(AR12="","",ROUND(BA12/AR12,4))) | BK12: =IF($A12="","",IF(AS12="","",ROUND(BB12/AS12,4))) | BL12: =IF($A12="","",IF(AT12="","",ROUND(BC12/AT12,4))) | BM12: =IF($A12="","",IF(AU12="","",ROUND(BD12/AU12,4))) | BN12: =IF($A12="","",IF(AV12="","",ROUND(BE12/AV12,4))) | BO12: =IF($A12="","",IF(AW12="","",ROUND(BF12/AW12,4))) | BP12: =IF($A12="","",IF(AX12="","",ROUND(BG12/AX12,4)))
U13: =IF($A13="","","X:\IMAGENES GEINPROD\"&$A13&".JPG") | V13: =IF($A13="","","X:\IMAGENES GEINPROD\PLANO ORIGINAL THERMIA\"&$A13&".pdf") | AY13: =IF($A13="","",ROUND(P13*CONFIGURACION!$B$2+IF(W13<>"",X13*IFERROR(VLOOKUP(W13,'DATOS COSTES POLIAMIDAS'!$A:$G,7,0),0),0)+IF(Y13<>"",Z13*IFERROR(VLOOKUP(Y13,'DATOS COSTES POLIAMIDAS'!$A:$G,7,0),0),0)+IF(AA13<>"",AB13*IFERROR(VLOOKUP(AA13,'DATOS COSTES POLIAMIDAS'!$A:$G,7,0),0),0)+IF(AC13<>"",AD13*IFERROR(VLOOKUP(AC13,'DATOS COSTES POLIAMIDAS'!$A:$G,7,0),0),0)+IF(AE13<>"",IFERROR(VLOOKUP(AE13,'DATOS COSTES MECANIZADOS'!$A:$F,6,0),0),0),4)) | AZ13: =IF($A13="","",ROUND(AY13+R13*CONFIGURACION!$B$6,4)) | BA13: =IF($A13="","",ROUND(AY13+R13*CONFIGURACION!$B$7,4)) | BB13: =IF($A13="","",ROUND(AY13+R13*CONFIGURACION!$B$5,4)) | BC13: =IF($A13="","",ROUND(AY13+R13*CONFIGURACION!$B$10+R13*T13*CONFIGURACION!$B$11,4)) | BD13: =IF($A13="","",ROUND(AY13+R13*CONFIGURACION!$B$8,4)) | BE13: =IF($A13="","",ROUND(AY13+R13*CONFIGURACION!$B$9,4)) | BF13: =IF($A13="","",ROUND(AY13+R13*CONFIGURACION!$B$13,4)) | BG13: =IF($A13="","",ROUND(AY13+R13*CONFIGURACION!$B$12,4)) | BH13: =IF($A13="","",IF(AP13="","",ROUND(AY13/AP13,4))) | BI13: =IF($A13="","",IF(AQ13="","",ROUND(AZ13/AQ13,4))) | BJ13: =IF($A13="","",IF(AR13="","",ROUND(BA13/AR13,4))) | BK13: =IF($A13="","",IF(AS13="","",ROUND(BB13/AS13,4))) | BL13: =IF($A13="","",IF(AT13="","",ROUND(BC13/AT13,4))) | BM13: =IF($A13="","",IF(AU13="","",ROUND(BD13/AU13,4))) | BN13: =IF($A13="","",IF(AV13="","",ROUND(BE13/AV13,4))) | BO13: =IF($A13="","",IF(AW13="","",ROUND(BF13/AW13,4))) | BP13: =IF($A13="","",IF(AX13="","",ROUND(BG13/AX13,4)))
U14: =IF($A14="","","X:\IMAGENES GEINPROD\"&$A14&".JPG") | V14: =IF($A14="","","X:\IMAGENES GEINPROD\PLANO ORIGINAL THERMIA\"&$A14&".pdf") | AY14: =IF($A14="","",ROUND(P14*CONFIGURACION!$B$2+IF(W14<>"",X14*IFERROR(VLOOKUP(W14,'DATOS COSTES POLIAMIDAS'!$A:$G,7,0),0),0)+IF(Y14<>"",Z14*IFERROR(VLOOKUP(Y14,'DATOS COSTES POLIAMIDAS'!$A:$G,7,0),0),0)+IF(AA14<>"",AB14*IFERROR(VLOOKUP(AA14,'DATOS COSTES POLIAMIDAS'!$A:$G,7,0),0),0)+IF(AC14<>"",AD14*IFERROR(VLOOKUP(AC14,'DATOS COSTES POLIAMIDAS'!$A:$G,7,0),0),0)+IF(AE14<>"",IFERROR(VLOOKUP(AE14,'DATOS COSTES MECANIZADOS'!$A:$F,6,0),0),0),4)) | AZ14: =IF($A14="","",ROUND(AY14+R14*CONFIGURACION!$B$6,4)) | BA14: =IF($A14="","",ROUND(AY14+R14*CONFIGURACION!$B$7,4)) | BB14: =IF($A14="","",ROUND(AY14+R14*CONFIGURACION!$B$5,4)) | BC14: =IF($A14="","",ROUND(AY14+R14*CONFIGURACION!$B$10+R14*T14*CONFIGURACION!$B$11,4)) | BD14: =IF($A14="","",ROUND(AY14+R14*CONFIGURACION!$B$8,4)) | BE14: =IF($A14="","",ROUND(AY14+R14*CONFIGURACION!$B$9,4)) | BF14: =IF($A14="","",ROUND(AY14+R14*CONFIGURACION!$B$13,4)) | BG14: =IF($A14="","",ROUND(AY14+R14*CONFIGURACION!$B$12,4)) | BH14: =IF($A14="","",IF(AP14="","",ROUND(AY14/AP14,4))) | BI14: =IF($A14="","",IF(AQ14="","",ROUND(AZ14/AQ14,4))) | BJ14: =IF($A14="","",IF(AR14="","",ROUND(BA14/AR14,4))) | BK14: =IF($A14="","",IF(AS14="","",ROUND(BB14/AS14,4))) | BL14: =IF($A14="","",IF(AT14="","",ROUND(BC14/AT14,4))) | BM14: =IF($A14="","",IF(AU14="","",ROUND(BD14/AU14,4))) | BN14: =IF($A14="","",IF(AV14="","",ROUND(BE14/AV14,4))) | BO14: =IF($A14="","",IF(AW14="","",ROUND(BF14/AW14,4))) | BP14: =IF($A14="","",IF(AX14="","",ROUND(BG14/AX14,4)))
U15: =IF($A15="","","X:\IMAGENES GEINPROD\"&$A15&".JPG") | V15: =IF($A15="","","X:\IMAGENES GEINPROD\PLANO ORIGINAL THERMIA\"&$A15&".pdf") | AY15: =IF($A15="","",ROUND(P15*CONFIGURACION!$B$2+IF(W15<>"",X15*IFERROR(VLOOKUP(W15,'DATOS COSTES POLIAMIDAS'!$A:$G,7,0),0),0)+IF(Y15<>"",Z15*IFERROR(VLOOKUP(Y15,'DATOS COSTES POLIAMIDAS'!$A:$G,7,0),0),0)+IF(AA15<>"",AB15*IFERROR(VLOOKUP(AA15,'DATOS COSTES POLIAMIDAS'!$A:$G,7,0),0),0)+IF(AC15<>"",AD15*IFERROR(VLOOKUP(AC15,'DATOS COSTES POLIAMIDAS'!$A:$G,7,0),0),0)+IF(AE15<>"",IFERROR(VLOOKUP(AE15,'DATOS COSTES MECANIZADOS'!$A:$F,6,0),0),0),4)) | AZ15: =IF($A15="","",ROUND(AY15+R15*CONFIGURACION!$B$6,4)) | BA15: =IF($A15="","",ROUND(AY15+R15*CONFIGURACION!$B$7,4)) | BB15: =IF($A15="","",ROUND(AY15+R15*CONFIGURACION!$B$5,4)) | BC15: =IF($A15="","",ROUND(AY15+R15*CONFIGURACION!$B$10+R15*T15*CONFIGURACION!$B$11,4)) | BD15: =IF($A15="","",ROUND(AY15+R15*CONFIGURACION!$B$8,4)) | BE15: =IF($A15="","",ROUND(AY15+R15*CONFIGURACION!$B$9,4)) | BF15: =IF($A15="","",ROUND(AY15+R15*CONFIGURACION!$B$13,4)) | BG15: =IF($A15="","",ROUND(AY15+R15*CONFIGURACION!$B$12,4)) | BH15: =IF($A15="","",IF(AP15="","",ROUND(AY15/AP15,4))) | BI15: =IF($A15="","",IF(AQ15="","",ROUND(AZ15/AQ15,4))) | BJ15: =IF($A15="","",IF(AR15="","",ROUND(BA15/AR15,4))) | BK15: =IF($A15="","",IF(AS15="","",ROUND(BB15/AS15,4))) | BL15: =IF($A15="","",IF(AT15="","",ROUND(BC15/AT15,4))) | BM15: =IF($A15="","",IF(AU15="","",ROUND(BD15/AU15,4))) | BN15: =IF($A15="","",IF(AV15="","",ROUND(BE15/AV15,4))) | BO15: =IF($A15="","",IF(AW15="","",ROUND(BF15/AW15,4))) | BP15: =IF($A15="","",IF(AX15="","",ROUND(BG15/AX15,4)))
... U202: =IF($A202="","","X:\IMAGENES GEINPROD\"&$A202&".JPG") | V202: =IF($A202="","","X:\IMAGENES GEINPROD\PLANO ORIGINAL THERMIA\"&$A202&".pdf") | AY202: =IF($A202="","",ROUND(P202*CONFIGURACION!$B$2+IF(W202<>"",X202*IFERROR(VLOOKUP(W202,'DATOS COSTES POLIAMIDAS'!$A:$G,7,0),0),0)+IF(Y202<>"",Z202*IFERROR(VLOOKUP(Y202,'DATOS COSTES POLIAMIDAS'!$A:$G,7,0),0),0)+IF(AA202<>"",AB202*IFERROR(VLOOKUP(AA202,'DATOS COSTES POLIAMIDAS'!$A:$G,7,0),0),0)+IF(AC202<>"",AD202*IFERROR(VLOOKUP(AC202,'DATOS COSTES POLIAMIDAS'!$A:$G,7,0),0),0)+IF(AE202<>"",IFERROR(VLOOKUP(AE202,'DATOS COSTES MECANIZADOS'!$A:$F,6,0),0),0),4)) | AZ202: =IF($A202="","",ROUND(AY202+R202*CONFIGURACION!$B$6,4)) | BA202: =IF($A202="","",ROUND(AY202+R202*CONFIGURACION!$B$7,4)) | BB202: =IF($A202="","",ROUND(AY202+R202*CONFIGURACION!$B$5,4)) | BC202: =IF($A202="","",ROUND(AY202+R202*CONFIGURACION!$B$10+R202*T202*CONFIGURACION!$B$11,4)) | BD202: =IF($A202="","",ROUND(AY202+R202*CONFIGURACION!$B$8,4)) | BE202: =IF($A202="","",ROUND(AY202+R202*CONFIGURACION!$B$9,4)) | BF202: =IF($A202="","",ROUND(AY202+R202*CONFIGURACION!$B$13,4)) | BG202: =IF($A202="","",ROUND(AY202+R202*CONFIGURACION!$B$12,4)) | BH202: =IF($A202="","",IF(AP202="","",ROUND(AY202/AP202,4))) | BI202: =IF($A202="","",IF(AQ202="","",ROUND(AZ202/AQ202,4))) | BJ202: =IF($A202="","",IF(AR202="","",ROUND(BA202/AR202,4))) | BK202: =IF($A202="","",IF(AS202="","",ROUND(BB202/AS202,4))) | BL202: =IF($A202="","",IF(AT202="","",ROUND(BC202/AT202,4))) | BM202: =IF($A202="","",IF(AU202="","",ROUND(BD202/AU202,4))) | BN202: =IF($A202="","",IF(AV202="","",ROUND(BE202/AV202,4))) | BO202: =IF($A202="","",IF(AW202="","",ROUND(BF202/AW202,4))) | BP202: =IF($A202="","",IF(AX202="","",ROUND(BG202/AX202,4)))

Sheet ACCESORIOS
A1: IDENTIFICACION | E1: GEINFOR | I1: COMERCIAL | N1: MINIMOS | Q1: PRECIOS | S1: CONTROL GENERACION
A2: REF | B2: FAMILIA | C2: CLASE/SERIE | D2: DENOMINACION | E2: TIPO | F2: CLASE | G2: GRUPO | H2: SUBGRUPO | I2: PROVEEDOR | J2: REF. PROV. | K2: LOTE HABITUAL | L2: PLAZO DIAS | M2: PARTIDA ARANC. | N2: MIN ALMACEN | O2: STOCK MINIMO | P2: STOCK MAXIMO | Q2: COSTE (euros/ud) | R2: PVP (euros/ud) | S2: ESTADO | T2: FECHA GENER. | U2: NOTAS

Sheet MAESTRO ACABADOS
A1: GRUPO | B1: SUFIJO | C1: DESCRIPCION | D1: DENOMINACION_2 | E1: ACTIVO
A2: 6 | B2: 052 | C2: GRIS ANTRACITA RAL 7016 | D2: RAL 7016 TX | E2: SI
A3: 6 | B3: 057 | C3: NEGRO RAL 9005 | D3: NEGRO RAL 9005 | E3: SI
A4: 6 | B4: 061 | C4: GRAFITO LV9407 | D4: GRAFITO LV9407 | E4: SI
A5: 6 | B5: 018 | C5: GRAFITO LV9407 (variante) | D5: GRAFITO LV9407 | E5: SI
A6: 9 | B6: 011 | C6: EFECTO MADERA ROBLE | D6: MADERA ROBLE | E6: SI
A7: 9 | B7: 012 | C7: EFECTO MADERA WENGUE | D7: MADERA WENGUE | E7: NO

Sheet SEGUIMIENTO
A1: CODIGO | B1: REF_BASE | C1: HOJA | D1: GRUPO | E1: SUFIJO | F1: FECHA | G1: RESULTADO | H1: DETALLE

Sheet CONFIGURACION
A1: PRECIO ALUMINIO (promedio extrusores)
A2: PRECIO ALU (euros/kg) | B2: 5.14 | C2: Promedio extrusores: 409, 415, 596, 249, 133, 1152, 1145, 210
A4: PRECIOS ACABADOS (euros por mm de perimetro)
A5: BL BLANCO | B5: 1.646 | C5: euros/m2 superficie (MAX grupo DATOS COSTES ACABADOS)
A6: PL PLATA | B6: 3.49 | C6: euros/m2 superficie (MAX grupo DATOS COSTES ACABADOS)
A7: BR BRONCE | B7: 5.66 | C7: euros/m2 superficie (MAX grupo DATOS COSTES ACABADOS)
A8: STD RAL ESTANDAR | B8: 2.707 | C8: euros/m2 superficie (MAX grupo DATOS COSTES ACABADOS)
A9: ESP RAL ESPECIAL | B9: 4.41 | C9: euros/m2 superficie (promedio activos >=4.29 grupos 5+7)
A10: ASP ANODIZADO ESP. | B10: 5.66 | C10: euros/m2 superficie (INOX LIJADO REPULIDO)
A11: LIJADO (x cara) | B11: 0.51 | C11: euros/m2 superficie x cara — solo ANOD ESP.
A12: MAD MADERA | B12: 6 | C12: euros/m2 superficie (fijo)
A13: BI BICOLOR | B13: 0 | C13: euros/m2 superficie — pendiente definir precio

Sheet MAESTRO TARIFAS
A1: TARIFA | B1: DESCRIPCION | C1: BASE | D1: MULTIPLICADOR | E1: UD VENTA | F1: IVA | G1: COEFICIENTE
A2: 40 | B2: TARIFA BASE | C2: T40 | D2: 1 | E2: 4 | F2: 21 | G2: 1/L
A3: 4010 | B3: 10% descuento sobre T40 | C3: T40 | D3: 0.9 | E3: 4 | F3: 21 | G3: 1/L
A4: 4015 | B4: 15% descuento sobre T40 | C4: T40 | D4: 0.85 | E4: 4 | F4: 21 | G4: 1/L
A5: 4020 | B5: 20% descuento sobre T40 | C5: T40 | D5: 0.8 | E5: 4 | F5: 21 | G5: 1/L
A6: 40000 | B6: Coste + 15% (barras) | C6: COSTE | D6: 1.15 | E6: 9 | F6: 21 | G6: 1
A7: 50000 | B7: Coste + 19% (barras) | C7: COSTE | D7: 1.19 | E7: 9 | F7: 21 | G7: 1
A8: 60000 | B8: Coste + 25% (barras) | C8: COSTE | D8: 1.25 | E8: 9 | F8: 21 | G8: 1
A9: 90000 | B9: Coste sin margen (barras) | C9: COSTE | D9: 1 | E9: 9 | F9: 21 | G9: 1
A10: 40100 | B10: Exportacion T40 x1,00 sin IVA | C10: T40 | D10: 1 | E10: 4 | F10: 0 | G10: 1/L
A11: 40103 | B11: Exportacion T40 x1,03 sin IVA | C11: T40 | D11: 1.03 | E11: 4 | F11: 0 | G11: 1/L
A12: 40106 | B12: Exportacion T40 x1,06 sin IVA | C12: T40 | D12: 1.06 | E12: 4 | F12: 0 | G12: 1/L
A13: 40109 | B13: Exportacion T40 x1,09 sin IVA | C13: T40 | D13: 1.09 | E13: 4 | F13: 0 | G13: 1/L
... A19: 40136 | B19: Exportacion T40 x1,36 sin IVA | C19: T40 | D19: 1.36 | E19: 4 | F19: 0 | G19: 1/L

Sheet VALIDACION TARIFAS
A1: VALIDACION TARIFAS — selecciona REF y ACABADO | H1: =IFERROR(MATCH(B2,PERFILES!$A:$A,0),"")
A2: REF: | C2: ACABADO: | D2: BT | H2: =IFERROR(MATCH(D2,{"BT","PL","BR","BL","ASP","STD","ESP","BI","MAD"},0),"") -> 1
A3: DENOMINACION: | B3: =IFERROR(INDEX(PERFILES!$C:$C,$H$1),"") | C3: LONGITUD: | D3: =IFERROR(INDEX(PERFILES!$Q:$Q,$H$1),"")
A4: PVP T40 (€/m): | B4: =IFERROR(INDEX(PERFILES!$BH:$BP,$H$1,$H$2),"") | C4: COSTE (€/m): | D4: =IFERROR(INDEX(PERFILES!$AY:$BG,$H$1,$H$2),"")
A6: TARIFA | B6: DESCRIPCION | C6: PVP (€/m o €/barra) | D6: UD VENTA | E6: IVA | F6: COEFICIENTE | G6: TIPO
A7: 40 | B7: TARIFA BASE | C7: =IFERROR(ROUND(B4*1,4),"") | D7: 4 | E7: 21 | F7: =IFERROR(ROUND(1/D3,6),"") | G7: NACIONAL
A8: 4010 | B8: 10% descuento sobre T40 | C8: =IFERROR(ROUND(B4*0.9,4),"") | D8: 4 | E8: 21 | F8: =IFERROR(ROUND(1/D3,6),"") | G8: NACIONAL
A9: 4015 | B9: 15% descuento sobre T40 | C9: =IFERROR(ROUND(B4*0.85,4),"") | D9: 4 | E9: 21 | F9: =IFERROR(ROUND(1/D3,6),"") | G9: NACIONAL
A10: 4020 | B10: 20% descuento sobre T40 | C10: =IFERROR(ROUND(B4*0.8,4),"") | D10: 4 | E10: 21 | F10: =IFERROR(ROUND(1/D3,6),"") | G10: NACIONAL
A11: 40000 | B11: Coste + 15% (barras) | C11: =IFERROR(ROUND(D4*D3*1.15,4),"") | D11: 9 | E11: 21 | F11: 1 | G11: NACIONAL
A12: 50000 | B12: Coste + 19% (barras) | C12: =IFERROR(ROUND(D4*D3*1.19,4),"") | D12: 9 | E12: 21 | F12: 1 | G12: NACIONAL
A13: 60000 | B13: Coste + 25% (barras) | C13: =IFERROR(ROUND(D4*D3*1.25,4),"") | D13: 9 | E13: 21 | F13: 1 | G13: NACIONAL
A14: 90000 | B14: Coste sin margen (barras) | C14: =IFERROR(ROUND(D4*D3*1,4),"") | D14: 9 | E14: 21 | F14: 1 | G14: NACIONAL
A15: 40100 | B15: Exportacion T40 x1,00 sin IVA | C15: =IFERROR(ROUND(B4*1,4),"") | D15: 4 | E15: 0 | F15: =IFERROR(ROUND(1/D3,6),"") | G15: EXPORTACION
A16: 40103 | B16: Exportacion T40 x1,03 sin IVA | C16: =IFERROR(ROUND(B4*1.03,4),"") | D16: 4 | E16: 0 | F16: =IFERROR(ROUND(1/D3,6),"") | G16: EXPORTACION
A17: 40106 | B17: Exportacion T40 x1,06 sin IVA | C17: =IFERROR(ROUND(B4*1.06,4),"") | D17: 4 | E17: 0 | F17: =IFERROR(ROUND(1/D3,6),"") | G17: EXPORTACION
A18: 40109 | B18: Exportacion T40 x1,09 sin IVA | C18: =IFERROR(ROUND(B4*1.09,4),"") | D18: 4 | E18: 0 | F18: =IFERROR(ROUND(1/D3,6),"") | G18: EXPORTACION
A19: 40112 | B19: Exportacion T40 x1,12 sin IVA | C19: =IFERROR(ROUND(B4*1.12,4),"") | D19: 4 | E19: 0 | F19: =IFERROR(ROUND(1/D3,6),"") | G19: EXPORTACION
A20: 40115 | B20: Exportacion T40 x1,15 sin IVA | C20: =IFERROR(ROUND(B4*1.15,4),"") | D20: 4 | E20: 0 | F20: =IFERROR(ROUND(1/D3,6),"") | G20: EXPORTACION
A21: 40118 | B21: Exportacion T40 x1,18 sin IVA | C21: =IFERROR(ROUND(B4*1.18,4),"") | D21: 4 | E21: 0 | F21: =IFERROR(ROUND(1/D3,6),"") | G21: EXPORTACION
A22: 40121 | B22: Exportacion T40 x1,21 sin IVA | C22: =IFERROR(ROUND(B4*1.21,4),"") | D22: 4 | E22: 0 | F22: =IFERROR(ROUND(1/D3,6),"") | G22: EXPORTACION
A23: 40133 | B23: Exportacion T40 x1,33 sin IVA | C23: =IFERROR(ROUND(B4*1.33,4),"") | D23: 4 | E23: 0 | F23: =IFERROR(ROUND(1/D3,6),"") | G23: EXPORTACION
A24: 40136 | B24: Exportacion T40 x1,36 sin IVA | C24: =IFERROR(ROUND(B4*1.36,4),"") | D24: 4 | E24: 0 | F24: =IFERROR(ROUND(1/D3,6),"") | G24: EXPORTACION

Sheet DATOS COSTES ACABADOS
A1: CODIGO_ARTICULO | B1: CLASE | C1: TIPO | D1: NORMA | E1: COSTE | F1: COEFICIENTE | G1: UNIDAD_INTERNA | H1: UNIDAD_EXTERNA | I1: FAMILIAPRODUCTO | J1: GRUPO | K1: PROVEEDOR | L1: ESTADO
A2: BLUE 600 SABLE | B2: 3 | C2: 2 | D2: EU | E2: 4.2936 | F2: 1 | G2: 5 | H2: 5 | I2: 0 | J2: 5 | K2: 428 | L2: 0
A3: RAL 7022 | B3: 3 | C3: 2 | D3: EU | E3: 2.707 | F3: 1 | G3: 5 | H3: 5 | I3: 0 | J3: 6 | K3: 428 | L3: 0
A4: RAL 6005 | B4: 3 | C4: 2 | D4: EU | E4: 4.2936 | F4: 1 | G4: 5 | H4: 5 | I4: 0 | J4: 5 | K4: 428 | L4: 0
A5: RAL 5005 | B5: 3 | C5: 2 | D5: EU | E5: 4.2936 | F5: 1 | G5: 5 | H5: 5 | I5: 0 | J5: 5 | K5: 428 | L5: 0
A6: BLUE 700 SABLE | B6: 3 | C6: 2 | D6: EU | E6: 4.4839 | F6: 1 | G6: 5 | H6: 5 | I6: 0 | J6: 5 | K6: 428 | L6: 0
A7: COBREOXIDO | B7: 3 | C7: 2 | D7: EU | E7: 4.4839 | F7: 1 | G7: 5 | H7: 5 | I7: 0 | J7: 7 | K7: 428 | L7: 60
A8: RAL 7035 TX | B8: 3 | C8: 2 | D8: EU | E8: 2.707 | F8: 1 | G8: 5 | H8: 5 | I8: 0 | J8: 6 | K8: 428 | L8: 0
A9: RAL 7034 | B9: 3 | C9: 2 | D9: EU | E9: 4.2936 | F9: 1 | G9: 5 | H9: 5 | I9: 0 | J9: 5 | K9: 428 | L9: 0
A10: RAL 7022 TX | B10: 3 | C10: 2 | D10: EU | E10: 2.5632 | F10: 1 | G10: 5 | H10: 5 | I10: 0 | J10: 6 | K10: 428 | L10: 0
A11: RAL 8011 | B11: 3 | C11: 2 | D11: EU | E11: 4.2936 | F11: 1 | G11: 5 | H11: 5 | I11: 0 | J11: 5 | K11: 428 | L11: 0
A12: ENCINA 7330 | B12: 3 | C12: 2 | D12: EU | E12: 5.995 | F12: 1 | G12: 5 | H12: 5 | I12: 0 | J12: 9 | K12: 429 | L12: 0
A13: RAL 5010 | B13: 3 | C13: 2 | D13: EU | E13: 2.707 | F13: 1 | G13: 5 | H13: 5 | I13: 0 | J13: 6 | K13: 428 | L13: 0
... A469: CEREZO CATEDRALES | B469: 3 | C469: 2 | D469: EU | E469: 7.4883 | F469: 1 | G469: 5 | H469: 5 | I469: 0 | J469: 9 | K469: 679 | L469: 0
A470: RAL 1021 MATE | B470: 3 | C470: 2 | E470: 4.2936 | F470: 1 | G470: 5 | H470: 5 | I470: 0 | J470: 5 | K470: 428 | L470: 0
A471: ROBLE RUSTICO TX | B471: 3 | C471: 2 | E471: 5.995 | F471: 1 | G471: 5 | H471: 5 | I471: 0 | J471: 9 | K471: 429 | L471: 0

Sheet DATOS COSTES POLIAMIDAS
A1: CODIGO_ARTICULO | B1: CLASE | C1: TIPO | D1: NORMA | E1: COSTE | F1: COEFICIENTE | G1: COSTE M/L | H1: UNIDAD_INTERNA | I1: UNIDAD_EXTERNA | J1: FAMILIAPRODUCTO | K1: GRUPO | L1: PROVEEDOR | M1: ESTADO
A2: POL202400 | B2: 0 | C2: 1 | D2: EU | E2: 2.148302 | F2: 0.15873 | G2: 0.34099998 | H2: 9 | I2: 4 | J2: 200 | K2: 0 | L2: 495 | M2: 0
A3: POL948700 | B3: 0 | C3: 1 | D3: EU | E3: 3.118503 | F3: 0.15873 | G3: 0.49499998 | H3: 9 | I3: 4 | J3: 200 | K3: 0 | L3: 495 | M3: 0
A4: POL276000 | B4: 0 | C4: 1 | D4: EU | E4: 3.646859 | F4: 0.15873016 | G4: 0.57886651 | H4: 9 | I4: 4 | J4: 200 | K4: 0 | L4: 495 | M4: 60
A5: POL977700 | B5: 0 | C5: 1 | D5: EU | E5: 3.08791 | F5: 0.15873016 | G5: 0.49014444 | H5: 9 | I5: 4 | J5: 200 | K5: 0 | L5: 495 | M5: 60
A6: POL979400 | B6: 0 | C6: 1 | D6: EU | E6: 3.654004 | F6: 0.15873 | G6: 0.58000005 | H6: 9 | I6: 4 | J6: 200 | K6: 0 | L6: 495 | M6: 0
A7: POL956059 | B7: 0 | C7: 1 | D7: EU | E7: 2.986203 | F7: 0.15873 | G7: 0.474 | H7: 9 | I7: 4 | J7: 200 | K7: 0 | L7: 495 | M7: 0
A8: POL495000 | B8: 0 | C8: 1 | D8: EU | E8: 4.167454 | F8: 0.15873 | G8: 0.66149997 | H8: 9 | I8: 4 | J8: 200 | K8: 0 | L8: 495 | M8: 0
A9: POL969859 | B9: 0 | C9: 1 | D9: EU | E9: 3.848674 | F9: 0.15873 | G9: 0.61090002 | H9: 9 | I9: 4 | J9: 200 | K9: 0 | L9: 495 | M9: 0
A10: POL375400 | B10: 0 | C10: 1 | D10: EU | E10: 9.59491 | F10: 0.15873 | G10: 1.5230001 | H10: 9 | I10: 4 | J10: 200 | K10: 0 | L10: 495 | M10: 0
A11: POL002316 | B11: 0 | C11: 1 | D11: EU | E11: 5.279405 | F11: 0.15873 | G11: 0.83799996 | H11: 9 | I11: 4 | J11: 200 | K11: 0 | L11: 495 | M11: 0
A12: POL425000 | B12: 0 | C12: 1 | D12: EU | E12: 6.911737 | F12: 0.15873016 | G12: 1.0971011 | H12: 9 | I12: 4 | J12: 200 | K12: 0 | L12: 495 | M12: 60
A13: POL430400 | B13: 0 | C13: 1 | D13: EU | E13: 7.114081 | F13: 0.15873016 | G13: 1.1292192 | H13: 9 | I13: 4 | J13: 200 | K13: 0 | L13: 495 | M13: 60
... A20: POL495001 | B20: 0 | C20: 1 | D20: EU | E20: 5.462105 | F20: 0.15873 | G20: 0.86699993 | H20: 9 | I20: 4 | J20: 200 | K20: 0 | L20: 495 | M20: 0

Sheet DATOS COSTES MECANIZADOS
A1: CODIGO_ARTICULO | B1: CLASE | C1: TIPO | D1: NORMA | E1: COSTE | F1: COSTE M/L | G1: COEFICIENTE | H1: UNIDAD_INTERNA | I1: UNIDAD_EXTERNA | J1: FAMILIAPRODUCTO | K1: GRUPO | L1: PROVEEDOR | M1: ESTADO | O1: 0.15873
A2: A0002032 | B2: 8 | C2: 1 | D2: EU | E2: 2.25 | F2: 0.3571425 | G2: 1 | H2: 4 | I2: 4 | J2: 107 | K2: 0 | L2: 481 | M2: 75
A3: A0002033 | B3: 8 | C3: 1 | D3: EU | E3: 1.24 | F3: 0.1968252 | G3: 1 | H3: 4 | I3: 4 | J3: 107 | K3: 0 | L3: 481 | M3: 75
A4: A0ME4015 | B4: 8 | C4: 1 | D4: EU | E4: 24.72 | F4: 3.9238056 | G4: 1 | H4: 1 | I4: 1 | J4: 0 | K4: 0 | L4: 1312 | M4: 0
A5: A0ME4017 | B5: 8 | C5: 1 | D5: EU | E5: 9.33 | F5: 1.4809509 | G5: 1 | H5: 1 | I5: 1 | J5: 0 | K5: 0 | L5: 1312 | M5: 0
A6: A0ME4025 | B6: 8 | C6: 1 | D6: EU | E6: 6.72 | F6: 1.0666656 | G6: 1 | H6: 1 | I6: 1 | J6: 0 | K6: 0 | L6: 1312 | M6: 0
A7: A0ME4645 | B7: 8 | C7: 1 | D7: EU | E7: 6.72 | F7: 1.0666656 | G7: 1 | H7: 1 | I7: 1 | J7: 0 | K7: 0 | L7: 1312 | M7: 0
A8: C062ME01 | B8: 8 | C8: 1 | D8: EU | E8: 8.04 | F8: 1.2761892 | G8: 1 | H8: 1 | I8: 1 | J8: 0 | K8: 0 | L8: 1312 | M8: 0
A9: C062ME02 | B9: 8 | C9: 1 | D9: EU | E9: 4.841 | F9: 0.76841193 | G9: 1 | H9: 1 | I9: 1 | J9: 0 | K9: 0 | L9: 1940 | M9: 0
A10: C062ME06 | B10: 8 | C10: 1 | D10: EU | E10: 15.45 | F10: 2.4523785 | G10: 1 | H10: 1 | I10: 1 | J10: 0 | K10: 0 | L10: 1940 | M10: 0
A11: ER72ME01 | B11: 8 | C11: 1 | D11: EU | E11: 20.49 | F11: 3.2523777 | G11: 1 | H11: 1 | I11: 1 | J11: 0 | K11: 0 | L11: 1312 | M11: 0
A12: ER72ME02 | B12: 8 | C12: 1 | D12: EU | E12: 8.91 | F12: 1.4142843 | G12: 1 | H12: 1 | I12: 1 | J12: 0 | K12: 0 | L12: 1312 | M12: 0
A13: ER72ME10 | B13: 8 | C13: 1 | D13: EU | E13: 18.39 | F13: 2.9190447 | G13: 1 | H13: 1 | I13: 1 | J13: 0 | K13: 0 | L13: 1312 | M13: 0
... A15: GR50ME10 | B15: 8 | C15: 1 | D15: EU | E15: 7.92 | F15: 1.2571416 | G15: 1 | H15: 1 | I15: 1 | J15: 0 | K15: 0 | L15: 1312 | M15: 0
